ShareLMAPI/__init__.py
ShareLMAPI/client/__init__.py
ShareLMAPI/client/client.py
ShareLMAPI/server/__init__.py
ShareLMAPI/server/load_model.py
ShareLMAPI/server/model_server.py
ShareLMAPI/server/server.py
local_model_api/__init__.py
local_model_api/client/__init__.py
local_model_api/client/client.py
local_model_api/sever/__init__.py
local_model_api/sever/load_model.py
local_model_api/sever/model_server.py
local_model_api/sever/server.py
ShareLMAPI-0.1.2.dist-info/LICENSE
ShareLMAPI-0.1.2.dist-info/METADATA
ShareLMAPI-0.1.2.dist-info/WHEEL
ShareLMAPI-0.1.2.dist-info/top_level.txt
ShareLMAPI-0.1.2.dist-info/RECORD
