Metadata-Version: 2.1
Name: ShareLMAPI
Version: 0.1.2
Summary: A local language model API for sharing models between programs.
Home-page: https://github.com/starpig1129/ShareLMAPI
Author: starpig1129
Author-email: james911129@gmail.com
Classifier: Programming Language :: Python :: 3
Classifier: License :: OSI Approved :: MIT License
Classifier: Operating System :: OS Independent
Requires-Python: >=3.10
License-File: LICENSE
Requires-Dist: fastapi
Requires-Dist: uvicorn
Requires-Dist: transformers
Requires-Dist: pytest
Requires-Dist: requests
Requires-Dist: peft
Requires-Dist: bitsandbytes
Requires-Dist: pydantic
